fuzz/__init__.py
fuzz/engine.py
fuzz/kernel.py
fuzz/memb_funcs.py
fuzz/operators.py
fuzz/rules.py
fuzzy_machines-0.1.5.dist-info/LICENSE
fuzzy_machines-0.1.5.dist-info/METADATA
fuzzy_machines-0.1.5.dist-info/WHEEL
fuzzy_machines-0.1.5.dist-info/top_level.txt
fuzzy_machines-0.1.5.dist-info/RECORD
